{
    "db-issuers": [
        {
            "PutRequest": {
                "Item": {
                    "sub_name": {
                        "S": "did:cheqd:mainnet:yG5tkXAzVq2p9mNLhz3r8KZuQW4yBXvM"
                    },
                    "organization_name": {
                        "S": "OneUni University"
                    },
                    "approval_status": {
                        "N": "1"
                    },
                    "logo_uri": {
                        "S": "data:image/png;base64,iVBORw0KGgoAAAANSUh..."
                    },
                    "homepage_uri": {
                        "S": "https://oneuni.edu"
                    },
                    "signed_sub_statement": {
                        "S": "eyJraWQiOiJvbmV1bmkta2V5MSIsInR5cC..."
                    }
                }
            }
        }
    ]
}